ModularBuilding/ModularBuilding.py
ModularBuilding/__init__.py
ModularBuilding/tests/__init__.py
ModularBuilding/tests/test.py
ModularBuilding/utils/__init__.py
ModularBuilding/utils/helper.py
ModularModelBuild-0.1.dist-info/LICENSE
ModularModelBuild-0.1.dist-info/METADATA
ModularModelBuild-0.1.dist-info/WHEEL
ModularModelBuild-0.1.dist-info/top_level.txt
ModularModelBuild-0.1.dist-info/RECORD
