Metadata-Version: 2.1
Name: ModularModelBuild
Version: 0.1
Summary: A python module to create linear or nonlinear numerical models for volumetric modular steel buildings using the finite element method (OpenSeesPy).
Home-page: https://github.com/mbbatukan/ModularModelBuild.git
Author: Mehmet Baris Batukan
Author-email: mbbatu@hotmail.com
Classifier: Development Status :: 3 - Alpha
Classifier: License :: OSI Approved :: MIT License
Classifier: Programming Language :: Python :: 3.11
License-File: LICENSE
